sushi/__init__.py
sushi/__main__.py
sushi/chapters.py
sushi/common.py
sushi/demux.py
sushi/keyframes.py
sushi/regression-tests.py
sushi/subs.py
sushi/wav.py
sushi_sub-0.6.2.dist-info/LICENSE
sushi_sub-0.6.2.dist-info/METADATA
sushi_sub-0.6.2.dist-info/WHEEL
sushi_sub-0.6.2.dist-info/entry_points.txt
sushi_sub-0.6.2.dist-info/top_level.txt
sushi_sub-0.6.2.dist-info/RECORD
