Metadata-Version: 2.1
Name: sushi-sub
Version: 0.6.2
Summary: Automatic subtitle shifter based on audio
Home-page: https://github.com/FichteFoll/Sushi
License: MIT
Project-URL: Documentation, https://github.com/tp7/Sushi/wiki
Project-URL: Fork Origin, https://github.com/tp7/Sushi
Platform: UNKNOWN
Classifier: Development Status :: 5 - Production/Stable
Classifier: License :: OSI Approved :: MIT License
Classifier: Programming Language :: Python :: 3
Classifier: Programming Language :: Python :: 3.5
Classifier: Programming Language :: Python :: 3.6
Classifier: Programming Language :: Python :: 3.7
Classifier: Programming Language :: Python :: 3.8
Classifier: Topic :: Multimedia :: Sound/Audio
Classifier: Topic :: Text Processing
Requires-Python: >=3.5
License-File: LICENSE
Requires-Dist: numpy (>=1.8)
